{
	"r":
	[
{
	"kezdet"					: "2018-01-01",
	"vege"						: "2018-01-29",
	"ceg"							: "Meló-Diák Dél Iskolaszövetkezet és minden mi szemnek szájnak ingere, meg a Ténainé Szaszák Veronika is",
	"uzemanyag_ar"		: "360",
	"tulaj"           : "Zákány Balázs",
	"tulaj_adoszam"   : "095127440",
	"tulaj_beosztas"  : "Fejlesztő",
	"tulaj_lakcim"    : "7761 Kozármisleny Viola u. 40/2",
	"tulaj_szul_ido"  : "1995-01-09",
	"tulaj_szul_hely" : "Miskolc",
	"tulaj_szolg_hely": "Pécs",
	"auto_rendszam"   : "NDN239",
	"auto_terfogat"   : "1394",
	"auto_marka"      : "Volkswagen",
	"auto_tipus"      : "Golf",
	"auto_fogyasztas" : "6.8",
	"auto_uzemanyag"  : "Benzin",
	"utak"						: [
													{
														"ut_id"   		: "151",
														"ut_datum"		: "2018-01-16 13:29:00",
														"ut_honnan" 	: "Pécs",
														"ut_hova"   	: "Budapest",
														"ut_cel"    	: "Fejlesztés",
														"ut_kezdo_km" : "33487",
														"ut_zaro_km"  : "33507",
														"ut_km"				: "20"
													},
													{
														"ut_id"   		: "155",
														"ut_datum"		: "2018-01-18 13:29:00",
														"ut_honnan" 	: "Budapest",
														"ut_hova"   	: "Budafok",
														"ut_cel"    	: "Kutya simogatás",
														"ut_kezdo_km" : "33507",
														"ut_zaro_km"  : "33533",
														"ut_km"				: "26"
													},
													{
														"ut_id"   		: "155",
														"ut_datum"		: "2018-01-18 13:29:00",
														"ut_honnan" 	: "Kozármisleny",
														"ut_hova"   	: "Nagyszombatújhely",
														"ut_cel"    	: "Tárgyalás",
														"ut_kezdo_km" : "33533",
														"ut_zaro_km"  : "33550",
														"ut_km"				: "17"
													}
											  ],
	"ossz_km" 				: "63",
	"ossz_koltseg"    : "1 298",
	"amortizacio"			: "9",
	"ossz_arotizacio" : "513",
	"global_osszeg"   : "1 811"
}
]
}
